midiutil/__init__.py
midiutil/MidiFile.py
midiutil/MidiFile3.py
miditime/__init__.py
miditime/miditime.py
miditime-1.1.3.dist-info/WHEEL
miditime-1.1.3.dist-info/DESCRIPTION.rst
miditime-1.1.3.dist-info/METADATA
miditime-1.1.3.dist-info/RECORD
miditime-1.1.3.dist-info/metadata.json
miditime-1.1.3.dist-info/top_level.txt
